molstat.py
tSNE/__init__.py
tSNE/tSNE.py
molstat-0.3.1.dist-info/LICENSE
molstat-0.3.1.dist-info/METADATA
molstat-0.3.1.dist-info/WHEEL
molstat-0.3.1.dist-info/entry_points.txt
molstat-0.3.1.dist-info/top_level.txt
molstat-0.3.1.dist-info/RECORD
