Metadata-Version: 2.1
Name: molstat
Version: 0.3.1
Summary: 用于计算分子性质和绘制性质分布的工具。
Home-page: https://github.com/autodataming/molstat
Author: Zhaoqiang Chen
Author-email: zqchen_simm@eqq.com
Classifier: Programming Language :: Python :: 3
Classifier: License :: OSI Approved :: MIT License
Classifier: Operating System :: OS Independent
Requires-Python: >=3.6
License-File: LICENSE
Requires-Dist: numpy
Requires-Dist: matplotlib
Requires-Dist: rdkit
